tg/__init__.py
tg/common/__init__.py
tg/common/_common/__init__.py
tg/common/_common/locations.py
tg/common/_common/s3helpers.py
tg/common/_common/warnings.py
tg/common/datasets/__init__.py
tg/common/datasets/access/__init__.py
tg/common/datasets/access/arch.py
tg/common/datasets/access/sql_wrapper.py
tg/common/datasets/access/zip_file_cache.py
tg/common/datasets/featurization/__init__.py
tg/common/datasets/featurization/featurization_job.py
tg/common/datasets/featurization/featurizer.py
tg/common/datasets/featurization/s3_destination.py
tg/common/datasets/local/__init__.py
tg/common/datasets/local/dataset.py
tg/common/datasets/local/downloader.py
tg/common/datasets/local/partitioned_dataset.py
tg/common/datasets/selectors/__init__.py
tg/common/datasets/selectors/amenities.py
tg/common/datasets/selectors/architecture.py
tg/common/datasets/selectors/combinators.py
tg/common/datasets/selectors/selector.py
tg/common/delivery/__init__.py
tg/common/delivery/jobs/__init__.py
tg/common/delivery/jobs/architecture.py
tg/common/delivery/jobs/ssh_docker_job_execution.py
tg/common/delivery/jobs/ssh_docker_job_routine.py
tg/common/delivery/packaging/__init__.py
tg/common/delivery/packaging/containering.py
tg/common/delivery/packaging/entry_point.py
tg/common/delivery/packaging/package.py
tg/common/delivery/packaging/packaging_dto.py
tg/common/delivery/training/__init__.py
tg/common/delivery/training/architecture.py
tg/common/delivery/training/sagemaker_execution.py
tg/common/delivery/training/sagemaker_training_routine.py
tg/common/delivery/training/ssh_docker_execution.py
tg/common/delivery/training/ssh_docker_training_routine.py
tg/common/ml/__init__.py
tg/common/ml/batched_training/__init__.py
tg/common/ml/batched_training/batcher.py
tg/common/ml/batched_training/batcher_strategy.py
tg/common/ml/batched_training/data_bundle.py
tg/common/ml/batched_training/extractors.py
tg/common/ml/batched_training/model_handler.py
tg/common/ml/batched_training/training_task.py
training_grounds-0.0.2.dist-info/METADATA
training_grounds-0.0.2.dist-info/WHEEL
training_grounds-0.0.2.dist-info/top_level.txt
training_grounds-0.0.2.dist-info/RECORD
