Metadata-Version: 2.1
Name: training-grounds
Version: 0.0.2
Summary: The framework for featurization and model training
Home-page: UNKNOWN
Author: UNKNOWN
Author-email: UNKNOWN
License: UNKNOWN
Platform: UNKNOWN
Requires-Dist: argon2-cffi (==20.1.0)
Requires-Dist: async-generator (==1.10)
Requires-Dist: attrs (==20.3.0)
Requires-Dist: backcall (==0.2.0)
Requires-Dist: bleach (==3.3.0)
Requires-Dist: boto3 (==1.17.47)
Requires-Dist: botocore (==1.20.47)
Requires-Dist: catboost (==0.25.1)
Requires-Dist: certifi (==2020.12.5)
Requires-Dist: cffi (==1.14.5)
Requires-Dist: chardet (==4.0.0)
Requires-Dist: click (==7.1.2)
Requires-Dist: cycler (==0.10.0)
Requires-Dist: decorator (==5.0.6)
Requires-Dist: defusedxml (==0.7.1)
Requires-Dist: deprecation (==2.1.0)
Requires-Dist: entrypoints (==0.3)
Requires-Dist: fastparquet (==0.5.0)
Requires-Dist: google-pasta (==0.2.0)
Requires-Dist: graphviz (==0.16)
Requires-Dist: greenlet (==1.0.0)
Requires-Dist: idna (==2.10)
Requires-Dist: importlib-metadata (==3.10.0)
Requires-Dist: ipykernel (==5.5.3)
Requires-Dist: ipython (==7.22.0)
Requires-Dist: ipython-genutils (==0.2.0)
Requires-Dist: ipywidgets (==7.6.3)
Requires-Dist: jedi (==0.18.0)
Requires-Dist: Jinja2 (==2.11.3)
Requires-Dist: jmespath (==0.10.0)
Requires-Dist: joblib (==1.0.1)
Requires-Dist: jsonpickle (==2.0.0)
Requires-Dist: jsonschema (==3.2.0)
Requires-Dist: jupyter-client (==6.1.12)
Requires-Dist: jupyter-core (==4.7.1)
Requires-Dist: jupyterlab-pygments (==0.1.2)
Requires-Dist: jupyterlab-widgets (==1.0.0)
Requires-Dist: kiwisolver (==1.3.1)
Requires-Dist: llvmlite (==0.36.0)
Requires-Dist: MarkupSafe (==1.1.1)
Requires-Dist: matplotlib (==3.4.1)
Requires-Dist: mistune (==0.8.4)
Requires-Dist: nbclient (==0.5.3)
Requires-Dist: nbconvert (==6.0.7)
Requires-Dist: nbformat (==5.1.3)
Requires-Dist: nest-asyncio (==1.5.1)
Requires-Dist: notebook (==6.3.0)
Requires-Dist: numba (==0.53.1)
Requires-Dist: numpy (==1.20.2)
Requires-Dist: packaging (==20.9)
Requires-Dist: pandas (==1.2.3)
Requires-Dist: pandocfilters (==1.4.3)
Requires-Dist: parso (==0.8.2)
Requires-Dist: patsy (==0.5.1)
Requires-Dist: pexpect (==4.8.0)
Requires-Dist: pickleshare (==0.7.5)
Requires-Dist: Pillow (==8.2.0)
Requires-Dist: plotly (==4.14.3)
Requires-Dist: presto-python-client (==0.7.0)
Requires-Dist: prometheus-client (==0.10.0)
Requires-Dist: prompt-toolkit (==3.0.18)
Requires-Dist: protobuf (==3.15.7)
Requires-Dist: protobuf3-to-dict (==0.1.5)
Requires-Dist: psycopg2-binary (==2.8.6)
Requires-Dist: ptyprocess (==0.7.0)
Requires-Dist: pyaml (==20.4.0)
Requires-Dist: pyarrow (==3.0.0)
Requires-Dist: pycparser (==2.20)
Requires-Dist: Pygments (==2.8.1)
Requires-Dist: pyparsing (==2.4.7)
Requires-Dist: pyrsistent (==0.17.3)
Requires-Dist: python-dateutil (==2.8.1)
Requires-Dist: python-dotenv (==0.17.0)
Requires-Dist: pytz (==2021.1)
Requires-Dist: PyYAML (==5.4.1)
Requires-Dist: pyzmq (==22.0.3)
Requires-Dist: requests (==2.25.1)
Requires-Dist: retrying (==1.3.3)
Requires-Dist: s3transfer (==0.3.6)
Requires-Dist: sagemaker (==2.33.0)
Requires-Dist: scikit-learn (==0.24.1)
Requires-Dist: scipy (==1.6.2)
Requires-Dist: seaborn (==0.11.1)
Requires-Dist: Send2Trash (==1.5.0)
Requires-Dist: six (==1.15.0)
Requires-Dist: sklearn (==0.0)
Requires-Dist: smdebug-rulesconfig (==1.0.1)
Requires-Dist: SQLAlchemy (==1.4.6)
Requires-Dist: statsmodels (==0.12.2)
Requires-Dist: terminado (==0.9.4)
Requires-Dist: testpath (==0.4.4)
Requires-Dist: threadpoolctl (==2.1.0)
Requires-Dist: thrift (==0.13.0)
Requires-Dist: torch (==1.8.1)
Requires-Dist: tornado (==6.1)
Requires-Dist: tqdm (==4.60.0)
Requires-Dist: traitlets (==5.0.5)
Requires-Dist: typing-extensions (==3.7.4.3)
Requires-Dist: urllib3 (==1.26.4)
Requires-Dist: wcwidth (==0.2.5)
Requires-Dist: webencodings (==0.5.1)
Requires-Dist: widgetsnbextension (==3.5.1)
Requires-Dist: yo-ds (==1.1.11)
Requires-Dist: yo-fluq (==1.1.11)
Requires-Dist: yo-fluq-ds (==1.1.11)
Requires-Dist: zipp (==3.4.1)
